{
    "type": "FeatureCollection",
    "bbox": [
        102.14391327,
        8.56276321,
        109.46911621,
        23.39264297
    ],
    "features": [
        {
            "bbox": [
                105.745295,
                21.036596,
                105.782244,
                21.060218
            ],
            "geometry": {
                "coordinates": [
                    [
                        [
                            [
                                105.770463,
                                21.056878
                            ],
                            [
                                105.770723,
                                21.056867
                            ],
                            [
                                105.770958,
                                21.056888
                            ],
                            [
                                105.771244,
                                21.056934
                            ],
                            [
                                105.771532,
                                21.05704
                            ],
                            [
                                105.771803,
                                21.05714
                            ],
                            [
                                105.77203,
                                21.057182
                            ],
                            [
                                105.772318,
                                21.057215
                            ],
                            [
                                105.772657,
                                21.057247
                            ],
                            [
                                105.772654,
                                21.05606
                            ],
                            [
                                105.772592,
                                21.055632
                            ],
                            [
                                105.772471,
                                21.055156
                            ],
                            [
                                105.77209,
                                21.054214
                            ],
                            [
                                105.77387,
                                21.054517
                            ],
                            [
                                105.782244,
                                21.05573
                            ],
                            [
                                105.78219,
                                21.055514
                            ],
                            [
                                105.782008,
                                21.054477
                            ],
                            [
                                105.781923,
                                21.053761
                            ],
                            [
                                105.781348,
                                21.046069
                            ],
                            [
                                105.781031,
                                21.041801
                            ],
                            [
                                105.780864,
                                21.039558
                            ],
                            [
                                105.780846,
                                21.039385
                            ],
                            [
                                105.780765,
                                21.038239
                            ],
                            [
                                105.780601,
                                21.036903
                            ],
                            [
                                105.780552,
                                21.036596
                            ],
                            [
                                105.778708,
                                21.036656
                            ],
                            [
                                105.776961,
                                21.036828
                            ],
                            [
                                105.775981,
                                21.037149
                            ],
                            [
                                105.772005,
                                21.038269
                            ],
                            [
                                105.769539,
                                21.039062
                            ],
                            [
                                105.763241,
                                21.041066
                            ],
                            [
                                105.761662,
                                21.041621
                            ],
                            [
                                105.761471,
                                21.041695
                            ],
                            [
                                105.761255,
                                21.04178
                            ],
                            [
                                105.751876,
                                21.045318
                            ],
                            [
                                105.750843,
                                21.045698
                            ],
                            [
                                105.747231,
                                21.046958
                            ],
                            [
                                105.745295,
                                21.04773
                            ],
                            [
                                105.7461,
                                21.048584
                            ],
                            [
                                105.746075,
                                21.048643
                            ],
                            [
                                105.745824,
                                21.048874
                            ],
                            [
                                105.745824,
                                21.048926
                            ],
                            [
                                105.746103,
                                21.04931
                            ],
                            [
                                105.746079,
                                21.049369
                            ],
                            [
                                105.745522,
                                21.050018
                            ],
                            [
                                105.745557,
                                21.050122
                            ],
                            [
                                105.745903,
                                21.050424
                            ],
                            [
                                105.746477,
                                21.050836
                            ],
                            [
                                105.747911,
                                21.051518
                            ],
                            [
                                105.748088,
                                21.051584
                            ],
                            [
                                105.748292,
                                21.05198
                            ],
                            [
                                105.748695,
                                21.052233
                            ],
                            [
                                105.747877,
                                21.054204
                            ],
                            [
                                105.749099,
                                21.054738
                            ],
                            [
                                105.748724,
                                21.055613
                            ],
                            [
                                105.751862,
                                21.056705
                            ],
                            [
                                105.753691,
                                21.05738
                            ],
                            [
                                105.7612,
                                21.060218
                            ],
                            [
                                105.761217,
                                21.060207
                            ],
                            [
                                105.761681,
                                21.059973
                            ],
                            [
                                105.762099,
                                21.059803
                            ],
                            [
                                105.763219,
                                21.059407
                            ],
                            [
                                105.76396,
                                21.059132
                            ],
                            [
                                105.764431,
                                21.058959
                            ],
                            [
                                105.765229,
                                21.058642
                            ],
                            [
                                105.766629,
                                21.058076
                            ],
                            [
                                105.767288,
                                21.057787
                            ],
                            [
                                105.767866,
                                21.057495
                            ],
                            [
                                105.768092,
                                21.057406
                            ],
                            [
                                105.768248,
                                21.057368
                            ],
                            [
                                105.768392,
                                21.057363
                            ],
                            [
                                105.768663,
                                21.05736
                            ],
                            [
                                105.768864,
                                21.057353
                            ],
                            [
                                105.769005,
                                21.057337
                            ],
                            [
                                105.769122,
                                21.057307
                            ],
                            [
                                105.769544,
                                21.057146
                            ],
                            [
                                105.769867,
                                21.057002
                            ],
                            [
                                105.770171,
                                21.056915
                            ],
                            [
                                105.770463,
                                21.056878
                            ]
                        ]
                    ]
                ],
                "type": "MultiPolygon"
            },
            "id": "xa3321.938",
            "properties": {
                "matinhxa": "1.937",
                "maxa": 937,
                "trung_tam_hc": "Tổ dân phố số 18, phường Phú Diễn",
                "dien_tich": 6.29,
                "ten_chi_tiet": "phường Phú Diễn - Thủ đô Hà Nội",
                "dan_so": "74603",
                "sat_nhap_tu": "Phường Phú Diễn, Phường Cổ Nhuế 1, Phường Mai Dịch, Phường Phúc Diễn"
            },
            "type": "Feature"
        }
    ]
}